EasyS7/DataBlock.py
EasyS7/PLC.py
EasyS7/Utility.py
EasyS7/__init__.py
EasyS7/DataTypes/DTUint.py
EasyS7/DataTypes/DTbool.py
EasyS7/DataTypes/DTdint.py
EasyS7/DataTypes/DTint.py
EasyS7/DataTypes/DTstring.py
EasyS7/DataTypes/DTtime.py
EasyS7/DataTypes/__init__.py
EasyS7-2.0.0.dist-info/LICENSE
EasyS7-2.0.0.dist-info/METADATA
EasyS7-2.0.0.dist-info/WHEEL
EasyS7-2.0.0.dist-info/top_level.txt
EasyS7-2.0.0.dist-info/RECORD
