Metadata-Version: 2.1
Name: EasyS7
Version: 2.0.0
Summary: Easy way to communicate with S7 series PLC.
Home-page: https://github.com/canerkaraguler/EasyS7
Author: Caner Karagüler
Author-email: caner.karaguler@gmail.com
License: UNKNOWN
Platform: UNKNOWN
Classifier: Programming Language :: Python :: 3
Classifier: License :: OSI Approved :: MIT License
Classifier: Operating System :: OS Independent
License-File: LICENSE
